openmairie.devtools-1.2.0-py3.10-nspkg.pth
openmairie/devtools/__init__.py
openmairie/devtools/omlogo.py
openmairie/devtools/omsvnexternals.py
openmairie/devtools/omtests.py
openmairie/devtools/templates/banner.svg.j2
openmairie/devtools/templates/logo.svg.j2
openmairie_devtools-1.2.0.dist-info/METADATA
openmairie_devtools-1.2.0.dist-info/WHEEL
openmairie_devtools-1.2.0.dist-info/entry_points.txt
openmairie_devtools-1.2.0.dist-info/namespace_packages.txt
openmairie_devtools-1.2.0.dist-info/top_level.txt
openmairie_devtools-1.2.0.dist-info/RECORD
