Metadata-Version: 2.4
Name: openmairie.devtools
Version: 1.2.0
Summary: openMairie Developer Tools
Home-page: http://www.openmairie.org/framework
Author: openMairie
Author-email: contact@openmairie.org
License: GPL
Project-URL: Source, https://gitlab.com/openmairie/openmairie.devtools/
Keywords: openMairie
Platform: any
Classifier: Programming Language :: Python
Classifier: Programming Language :: Python :: 3
Classifier: Programming Language :: Python :: 3 :: Only
Classifier: License :: OSI Approved :: GNU General Public License (GPL)
Requires-Dist: setuptools
Requires-Dist: jinja2
Requires-Dist: unidecode
Dynamic: author
Dynamic: author-email
Dynamic: classifier
Dynamic: description
Dynamic: home-page
Dynamic: keywords
Dynamic: license
Dynamic: platform
Dynamic: project-url
Dynamic: requires-dist
Dynamic: summary
